LICENSE.txt
MANIFEST.in
README.rst
setup.cfg
setup.py
happy_couple/__init__.py
happy_couple/happy_couple.py
happy_couple.egg-info/PKG-INFO
happy_couple.egg-info/SOURCES.txt
happy_couple.egg-info/dependency_links.txt
happy_couple.egg-info/requires.txt
happy_couple.egg-info/top_level.txt
happy_couple/lines_only/small_head.png
happy_couple/lines_only/th_view_01.png
happy_couple/lines_only/th_view_02.png
happy_couple/lines_only/th_view_03.png
happy_couple/lines_only/th_view_03_normal.png
happy_couple/lines_only/th_view_04.png
happy_couple/lines_only/th_view_05.png
happy_couple/lines_only/th_view_06.png
happy_couple/lines_only/th_view_07.png
happy_couple/lines_only/th_view_08.png
happy_couple/lines_only/th_view_09.png
happy_couple/lines_only/th_view_10.png
happy_couple/lines_only/th_view_11.png
happy_couple/lines_only/th_view_12.png
happy_couple/lines_only/th_view_13.png
happy_couple/lines_only/waiting_woman.png
happy_couple/lines_only/walking_man_01.png
happy_couple/lines_only/walking_man_02.png
happy_couple/lines_only/walking_man_03.png
happy_couple/sounds/smb_coin.wav
happy_couple/sounds/smb_jump.wav
happy_couple/sounds/smb_touch.wav