Metadata-Version: 2.1
Name: happy-couple
Version: 0.1.1
Summary: cover of scene from revenge of the nerds
Home-page: https://github.com/streanger/happy_couple
Author: streanger
Author-email: divisionexe@gmail.com
License: MIT
Platform: UNKNOWN
Classifier: Programming Language :: Python :: 3
Classifier: License :: OSI Approved :: MIT License
Classifier: Operating System :: OS Independent
